lsbinit/__init__.py
lsbinit/common.py
lsbinit/lock.py
lsbinit/pid.py
lsbinit-0.1.post7.dist-info/DESCRIPTION.rst
lsbinit-0.1.post7.dist-info/METADATA
lsbinit-0.1.post7.dist-info/RECORD
lsbinit-0.1.post7.dist-info/WHEEL
lsbinit-0.1.post7.dist-info/metadata.json
lsbinit-0.1.post7.dist-info/top_level.txt
