Metadata-Version: 2.0
Name: lsbinit
Version: 0.1.post7
Summary: Linux init scripts handler
Home-page: http://github.com/djtaylor/python-lsbinit
Author: David Taylor
Author-email: djtaylor13@gmail.com
License: GPLv3
Keywords: feedback terminal shell init service
Platform: UNKNOWN
Classifier: Development Status :: 3 - Alpha
Classifier: Environment :: Console
Classifier: License :: OSI Approved :: GNU General Public License v3 or later (GPLv3+)
Classifier: Natural Language :: English
Classifier: Operating System :: POSIX
Classifier: Programming Language :: Python
Classifier: Topic :: Terminals
Classifier: Topic :: System :: Systems Administration
Classifier: Topic :: System :: Shells
